docs.py
src/duckduckgo_cli/main.py
duckduckgo_cli-0.0.1.dist-info/METADATA
duckduckgo_cli-0.0.1.dist-info/WHEEL
duckduckgo_cli-0.0.1.dist-info/entry_points.txt
duckduckgo_cli-0.0.1.dist-info/licenses/LICENSE
duckduckgo_cli-0.0.1.dist-info/RECORD
