Metadata-Version: 2.1
Name: duckduckgo-cli
Version: 0.0.1
Summary: Search duckduckgo in terminal open browser
Project-URL: Homepage, https://github.com/yrom1/duckduckgo-cli
Project-URL: Bug Tracker, https://github.com/yrom1/duckduckgo-cli/issues
Author-email: Ryan Moore <ryanm.inbox@gmail.com>
License-File: LICENSE
Classifier: License :: OSI Approved :: MIT License
Classifier: Operating System :: OS Independent
Classifier: Programming Language :: Python :: 3
Requires-Python: >=3
